{"summary":"Sherlock Holmes comes to the aid of his friend Henry Baskerville, who is under a family curse and menaced by a demonic dog that prowls the bogs near his estate and murders people.","cast":"Ian Richardson|Donald Churchill|Denholm Elliott|Glynis Barber|Brian Blessed|Eleanor Bron|Edward Judd|Ronald Lacey|Martin Shaw|Connie Booth|Eric Richard|Michael Burrell|Cindy O'Callaghan|Peter Rutherford|Francesca Gonshaw|David Langton|Nicholas Clay|Kerry Shale","keywords":"murder|dog|place name in title|animal in title|supernatural power","year":1983,"director":"Director: Douglas Hickox","genre":"Crime|Horror|Mystery|Thriller","rating":6.6,"title":"El perro de los Baskerville"}