{"summary":"A travelling theater group find so much action going on behind-the-scenes, they almost ruin the performances.","cast":"Carol Burnett|Michael Caine|Denholm Elliott|Julie Hagerty|Marilu Henner|Mark Linn-Baker|Christopher Reeve|John Ritter|Nicollette Sheridan|Katie Rich|Zoe R. Cassavetes|Kim Sebastian|Louise Stratten|J. Christopher Sullivan|Kimberly Neville|Cleveland O'Neal III|Roger Michelson|Joe Hanna|Rosie De Sanctis|Jack McCall|Keith Crowningshield|Andrew Mapp|Diana Agostini|Bronson Dudley|Drummond Erskine|Roger Armstrong|Dick Corman|Wendy Wilson|Matt Gottlieb|Dana Marley|Forest Baker|Jorga Caye|Don Roberts","keywords":"argument|actor|backstage|theatre|reference to william shakespeare","year":1992,"director":"Director: Peter Bogdanovich","genre":"Comedy","rating":7.6,"title":"¡Qué ruina de función!"}