{"summary":"An editor asks Deven, a teacher who loves Urdu poetry, to interview poet Nur Shahjehanabadi, an aging whale of a man. Deven goes to Bhopal from Mirpur to meet Nur, of whom he is in awe. He ... See full summary »","cast":"Shashi Kapoor|Shabana Azmi|Om Puri|Sushma Seth|Neena Gupta|Tinnu Anand|Prayag Raj|Parikshit Sahni|Sagar Arya|Alakh Nandan|Yusuf Khurram|Riju Bajaj|Maza Bi|Nayeem Hafizka|Virendra Saxena|Sameer Mitha|Rupinder Kaur|Shahid Masood|Tiblu Khan|Afzal Khan|Manzoor Ahtesham|Amit Goswani|Pragya Mekherjee|Umer Sahib|Gopal Janum|Ramratan Sen|Munawwar Noqwi|Sanjay Mohan Sagar|Farhan Khan|Anik Day|Samir Feroz|Syed Zaheer Ul-Hasan|Sulbha Chaurasia|Farooq Khan|Chunnu Ashfaque Ahmed Khan|Ustad Saeed Khan|Mustafa Taj|Nasir Mirza|Siddharth|Shashank Mukherjee|Prashant Khirwadkar|Razzak Siddiqui|Mohamad Ali|Kaynat Kauser|Parveen Rehman|Afzal Hussein|Ishak Khan|Amjad Khan|Mohd. Jail Mansoor|Shakendra Yadav|Nikhil Das|Anil Mulchandani|Shubha Bannerjee|Samta Choudhary|Jyoti Mishra|Swastika Chakraborty|Aruna Shrivastava|Megha Pal|Habib Bhopali|Nafisa Sharma|Sajid Mitha|Humayun Khan|K.S. Mehta","keywords":"poet|second wife|poetry|drink|bhopal","year":1994,"director":"Director: Ismail Merchant","genre":"Comedy|Drama","rating":7.1,"title":"In Custody"}