{"summary":"Danny is a smart little girl. She lives at the track where her uncle is a horse trainer. She knows her uncle needs just one great horse to make his name.","cast":"Leelee Sobieski|Robert Urich|Ron Brice|Gary Basaraba|Erik Jensen|Ed Bruce|Karen Carlson|Brian Michael|Ed Grady|Randal Patrick|Stuart Greer|James L. Davis|Emerson St. John|Robert Wallace|Bob C. Cooke|Jon Shelton|Timothy Paul Taylor","keywords":"horse|horse actor|character name in title","year":1995,"director":"Director: Dick Lowry","genre":"Drama|Family","rating":6.2,"title":"Un caballo para Danny"}