{"summary":"Two women who are abandoned by their husbands, find love and solace in each other.","cast":"Karishma Jhalani|Ramanjeet Kaur|Dilip Mehta|Javed Jaffrey|Nandita Das|Vinay Pathak|Kushal Rekhi|Shabana Azmi|Ranjit Chowdhry|Kulbhushan Kharbanda|Alice Poon|Ram Gopal Bajaj|Ravinder Happy|Devyani Saltzman|Sunil Chhabra|Avijit Dutt|Shasea Bahadur|Meher Chand|Bahadur Chand|Puran|Sohan Lal|Meher|Amarjit Chand|Karam Chand|Kabir Chowdhury|Laurence Côte","keywords":"repression|newlywed|marriage|fire|servant","year":1996,"director":"Director: Deepa Mehta","genre":"Drama|Romance","rating":7.2,"title":"Fuego (Fire)"}