{"summary":"A woman discovers a tragic love letter in a bottle on a beach, and is determined to track down its author.","cast":"Kevin Costner|Robin Wright|Paul Newman|John Savage|Illeana Douglas|Robbie Coltrane|Jesse James|Bethel Leslie|Tom Aldredge|Viveka Davis|Raphael Sbarge|Richard Hamilton|Rosemary Murphy|Steven Eckholdt|Susan Brightbill|Patricia Belcher|Steve Mellor|Lance Gilbert|Jennifer Lamb|Hayden Panettiere|Walt MacPherson|Justin DiPego|Meagan Riley-Grant|Karen Fowler|Caleb Deschanel|Mauricio Ochmann|Anthony Genovese|Elizabeth Guindi|Donald Watson|W. Clapham Murray|Gregg Trzaskowski|Robert Sauvayre-Tarlow|Philip Traynor|Daniel V. Trefts|Christina Bergstrom|Norman Fessler|David Paris|Robert Kenney|Sally Fay Cottingham|Marcello Robinson|Darla Rothman","keywords":"letter|sex|grief|bottle|love","year":1999,"director":"Director: Luis Mandoki","genre":"Drama|Romance","rating":6.3,"title":"Mensaje en una botella"}