{"summary":"Bojack is a demon who was freed from prison when King Kai's planet was destroyed. Now, without his father Goku by his side, can Gohan save the Earth?","cast":"Masako Nozawa|Toshio Furukawa|Mayumi Tanaka|Takeshi Kusao|Tôru Furuya|Hirotaka Suzuoki|Hiroko Emori|Ryô Horikawa|Daisuke Gôri|Hiromi Tsuru|Naoko Watanabe|Naoki Tatsuta|Kôhei Miyauchi|Tesshô Genda|Toshiyuki Morikawa|Tomoko Maruo|Hisao Egawa|Jôji Yanami|Sean Schemmel|Christopher Sabat|Bob Carter|Stephanie Nadolny|Eric Vale|Sonny Strait|Cynthia Cranz|Chris Rager|Robert McCollum|Christopher Bevins|Colleen Clinkenbeard|Iman Nazemzadeh|Tiffany Vollmer|Bradford Jackson|Mike McFarland|John Burgmeier|Brice Armstrong|Grant James|Jamie Marchi|Michael Terry|Amber Cotton|Dameon Clarke|Justin Pate|Ahmad Khafe|Grace Roiyo|Monika Antonelli|Paul Bandey|Jodi Forrest|David Gasman|Sharon Mann|Edward Marcus|Doug Rand","keywords":"martial arts tournament|martial arts|multiple english dubs|based on comic book|based on manga","year":1993,"director":"Director: Yoshihiro Ueda","genre":"Animation|Action|Adventure|Fantasy|Sci-Fi|Thriller","rating":7.2,"title":"Dragon Ball Z: Los guerreros de plata"}