{"summary":"The film tells the story of two very popular Finnish singer\/songwriters: Tapio Rautavaara (Tapio Liinoja) and Repe Helismaa (Martti Suosalo), who worked together until their relationship ... See full summary »","cast":"Tapio Liinoja|Martti Suosalo|Heikki Nousiainen|Anna Haaranen|Heidi Herala|Ari Wirta|Pertti Koivula|Aulis Rosendahl|Martti Katajisto|Matti Mäntylä|Raimo Grönberg|Ilkka Koivula|Kai Lehtinen|Ritva Kanerva|Tuija Piepponen|Esko Nikkari|Leena Suomu|Maritta Viitamäki|Juha Laitila|Hilkka Ollikainen|Kai Tanner|Kasperi Tanner|Kaj Vartio|Valle Yritys|Taneli Rinne|Kalevi Haapoja|Timo Nissi|Marja Korhonen|Jan-Peter Nyquist|Tomi Salmela|Pekka Lukka|Aleksander Anria|Eija Nousiainen|Aarre Karén|Marjukka Mattila|Tia Nurminen|Merika Koivusalo|Roope Sivander|Riina Koivusalo|Juha Jalonen|Miika-Markus Hömpi|Anna-Maija Nissi|Raino Rissanen|Risto Salmi|Väinö Välkky|Titta Antti-Poika|Tuula Keuru|Kielo Tommila|Severi Koivusalo|Jukka Wahlroos|Antti Vartiala|Tuula Pennanen|Seppo Sallinen|Markku Leino|Hannu Kivioja|Harri Ekonen|Sirkka-Liisa Leskinen-Toiviainen|Mauno Käpyaho|Antti Majanlahti|Mika Nuojua|Seppo Helenius|Matti Heinivaho|Reijo Innanen|Reijo Rantanen|Raimo Liukko|Maarit Peltomaa|Pirkko Uitto|Jari Järveläinen|Jari Peltoniemi|Jenna Ullvén|Kirsi Nurminen|Salme Halmetoja|Sofie Henriksén|Anne Ketola|Yasmin Samaletdin|Matti Vannekari|Pekka Lehtimäki|Heikki Lähteenmäki|Samuli Koivusalo","keywords":"friend|suicide|post war|pekka ja patka|friendship","year":1999,"director":"Director: Timo Koivusalo","genre":"Biography|Drama|Music","rating":6.7,"title":"El vagabundo y el cisne"}