{"summary":"The manager of England's national football unexpectedly succumbs to a heart attack, and suddenly the search is on for a replacement. Most people who seem qualified for the position have the... See full summary »","cast":"Ricky Tomlinson|Amanda Redman|Bradley Walsh|Philip Jackson|Phill Jupitus|Dean Lennox Kelly|Martin Bashir|Robbie Gee|Pelé|Kevin Piper|Robert Putt|Malcolm Terris|Philip Dunbar|Ulrich Thomsen|Lloyd McGuire|Geoff Bell|Sidney Livingstone|Chris Boyle-McQuarry|Ian Lindsay|Tony Nyland|Geoffrey Hutchings|Danny Tennant|Natasha Kaplinsky|Iain Rogerson|Angela Curran|Sean Gilder|Nigel Lindsay|Mark Burdis|John Smith|Scott Mean|Julian Ballantine|Dean Holness|John Alford|Terry Kiely|Peter McGillycuddy|Toby Redwood|Andy Ansah|Thomas Kenyon|Robert Campion|Alex Lawler|Dion Osborne|Danny Husbands|Declan Perkins|Sue Barker|Phil Gridelet|Dickie Bird|Alan Renwick|Keith Allen|Adrian James|Gabby Logan|Mark O'Donoghue|Peter McGillycuddy Sr.|Barry Venison|Ronaldo|Richard Guest|Clive Tyldesley|Martin Tyler|Jenny Frost|Rob Sprackling|Liz McClarnon|Kim Durham|Robert Hudson|Des Hamilton|Paul Rattray|Neil Peplow|Glenn Mulhern|Stephen Walters|Paul McNeilly|Paul Murphy|Phil Penfold|Charlie Thompson|Tony Harmer|Narcisa Tamborindeguy|Vincent Marzello|Scott Richardson|Alan Green|Brian Moore|Daniel Amokachi|Roberto Baggio|David Batty|David Beckham|Greg Bennett|David J. Bremner|Zeca Carvalho|Martin Dahlin|Andy Ewings|Glenn Hoddle|Kevin Hudson|Mark Lawrenson|Diego Maradona|Ralph G. Morse|Michael Owen|Adrian Paine|Florin Raducioiu|Eoin Wrixon|Tim Bishop|Duane Fierro|Kevin Keegan|Nic Martin","keywords":"pixelated nudity|norwich england|london england|mockumentary|england","year":2001,"director":"Director: Steve Barron","genre":"Comedy|Sport","rating":6.9,"title":"Mike Bassett: England Manager"}