{"summary":"A Ukrainian village must suddenly contend with the Nazi invasion of June 1941.","cast":"Anne Baxter|Dana Andrews|Walter Huston|Walter Brennan|Ann Harding|Jane Withers|Farley Granger|Erich von Stroheim|Dean Jagger|Eric Roberts|Carl Benton Reid|Ann Carter|Esther Dale|Ruth Nelson|Paul Guilfoyle|Martin Kosleck|Tonio Selwart|Peter Pohlenz|Gene O'Donnell|Robert Lowery|Frank Wilcox|Loudie Claar|Lynn Winthrop|Charles Bates|Florence Auer|John Bagni|Art Baker|John Beverly|Bill Borzage|Eric Braunsteiner|Ruth Brennan|Frederic Brunn|Edward Burns|Lane Chandler|Edmund Cobb|Grace Cunard|Sonia Darrin|Emma Dunn|Martin Faust|Al Ferguson|Constant Franke|Clair Freeman|Inna Gest|Henry Hall|Tommy Hall|Teddy Infuhr|John Judd|Ilia Khmara|George Kole|Ann Kunde|Tamara Laub|Grace Lenard|George Lynn|Ronn Marvin|Jerry Mickelsen|Ralph Montgomery|Bill Nestell|Georgie Nokes|Sarah Padden|Patricia Parks|Jack Perrin|Minna Phillips|Francis Pierlot|Serge Protzenko|Tommy Rall|William Sabbot|Ferdinand Schumann-Heink|Carl Sepulveda|Clarence Straight|Harry Strang|Ray Teal|Joyce Tucker|Dorothy Vernon|Jack Vlaskin|Marie Vlaskin|William Walker|Crane Whitley","keywords":"nazi soldier|nazi|doctor|communist|alternate history","year":1943,"director":"Director: Lewis Milestone","genre":"Drama|Romance|War","rating":5.9,"title":"La estrella del norte"}