{"summary":"Alexander, the King of Macedonia and one of the greatest army leaders in the history of warfare, conquers much of the known world.","cast":"Anthony Hopkins|David Bedella|Jessie Kamm|Angelina Jolie|Val Kilmer|Fiona O'Shaughnessy|Connor Paolo|Patrick Carroll|Brian Blessed|Peter Williamson|Morgan Christopher Ferris|Rob Earley|Aleczander Gordon|Christopher Plummer|Gary Stretch|John Kavanagh|Nick Dunning|Marie Meyer|Mick Lally|Colin Farrell|Jared Leto|Elliot Cowan|Joseph Morgan|Ian Beattie|Jonathan Rhys Meyers|Denis Conway|Neil Jackson|Garrett Lombard|Chris Aberdein|Rory McCann|Michael Dixon|Tim Pigott-Smith|Raz Degan|Erol Sander|Stéphane Ferrara|Tadhg Murphy|Jean Le Duc|Francisco Bosch|Annelise Hesme|Tsouli Mohammed|Toby Kebbell|Laird Macintosh|Rosario Dawson|Rab Affleck|Féodor Atkine|Harry Kent|Sam Green|Bin Bunluerit|Jaran Ngamdee|Brian McGrath|Suzanne Bullock|Kate Eloise Whitfield|Gillian Grueber|Michelle Lukes|Anjali Mehra|Anthony Jean Marie Kurt|Marta Barahona|Monica Zamora|Benny Maslov|Tania Matos|Leighton Morrison|Isaac Mullins|Monica Perego|Matthew Powell|Adil Akram|Benjamín Benítez|Anthony James Berowne|Nicolas D. Blake|Max Bollinger|Jason Croot|Fahar Faizaan|Charles Haigh|Abbie Hirst|Charlie Hollway|Rowley Irlam|Joey Jeetun|David Leon|Evelina Manna|Desmond O'Neill|Greg Orvis|Lee Anthony Parnell|Genevieve Redmond|John Reynolds|Peter Rnic|Oliver Stone|John Whitby","keywords":"greek|ancient greece|gay|macedonia|323 b.c.","year":2004,"director":"Director: Oliver Stone","genre":"Action|Biography|Drama|History|War","rating":5.6,"title":"Alejandro Magno"}