{"summary":"Inuyasha and company have finally destroyed Naraku. And each start to go in their separate ways. Sango going to find her younger brother Kohaku; Miroku back to his old home; Inuyasha, ... See full summary »","cast":"Kappei Yamaguchi|Satsuki Yukino|Kôji Tsujitani|Houko Kuwashima|Kumiko Watanabe|Noriko Hidaka|Ken'ichi Ogata|Toshiyuki Morikawa|Izumi Ôgami|Yukana Nogami|Akiko Yajima|Toshihiko Nakajima|Yuzuru Fujimoto|Yûji Ueda|Akiko Nakagawa|Kaori Shimizu|Yûki Masuda|Nami Okamoto|Eisuke Yoda|Takako Matsumoto|Tadahisa Saizen|Tomoya Kawai|Tarou Masuoka|Mieko Harada|Richard Ian Cox|Paul Dobson|Saffron Henderson|Pam Hyatt|Janyse Jaud|Willow Johnson|Terry Klassen|Danny McKinnon|Jillian Michaels|Kirby Morrow|Nicole Oliver|Kelly Sheridan|Moneca Stori|Cathy Weseluck|Alec Willows|Matt Smith","keywords":"older actors younger roles|mysticism|bodily possession|half demon|yokai","year":2002,"director":"Director: Toshiya Shinohara","genre":"Action|Animation|Comedy|Romance","rating":7.5,"title":"InuYasha: El castillo de sueños en el espejo"}