{"summary":"An adaptation of Bishop T.D. Jakes' self-help novel, chronciling a woman's struggle to come to terms with her legacy of abuse, addiction and poverty.","cast":"Kimberly Elise|Loretta Devine|Debbi Morgan|Michael Boatman|Clifton Powell|Idalis DeLeon|T.D. Jakes|Sean Blakemore|Jordan Moseley|Philip Bolden|Destiny Edmond|Louisa Abernathy|Amy Aquino|Malik Barnhardt|Porscha Coleman|Conni Marie Brazelton|Lanier Edwards|Ellia English|Mary Evans|Jozella Reed|Chip Fields|Bergen Williams|LaRita Shelby|Melanie Comarcho|Masasa Moyo|Mo McRae|Maura Gale|Ricky Harris|Kennedy McCullough|Kymberly Newberry|Roxanne Reese|Chaz Lamar Shepherd|Alex Thomas|Dan White|Arturo Anderson|Damon Butler|Michael Dotson|Clyde Goins|Marion Koh|Micah Stampley|Rodney Washington|Kevin Long","keywords":"bishop|poverty|abuse|flashback|death","year":2004,"director":"Director: Michael Schultz","genre":"Drama","rating":6.7,"title":"Woman Thou Art Loosed"}