{"summary":"During the blood-soaked Turkish invasion in Cyprus in 1974, a company of soldiers end up in the sun-kissed island of Samothrace in the northern Aegean Sea, against the backdrop of the violent and terrible events that shatter the country.","cast":"Renos Haralambidis|Costas Santas|Dimitris Piatas|Stavros Nikolaidis|Thodoris Petropoulos|Rigas Axelos|Ilias Katevas|Malamatenia Gotsi|Sofia Sotiriou|Yorgos Kavgalakis|Vasilis Lemonakis|Nikos Pantelidis|Tasos Palatzidis|Giorgos Vouzoukidis|Marios Ioannou|Anthi Tsangalidou|Stefanos Mondelos|Alexandros Pontikakis|Avgoustinos Remoundos|Manolis Matthaiou|Zaharenia Spiliou|Konstadinos Syrakis|Anestis Geronikolakis|Makis Hanos|Dimitris Markou|Spyros Papatriantafyllou|Anestis Stagoglou|Giorgos Tsipos","keywords":"island|zeibekiko|watermelon|radio broadcasting|place name in title","year":2003,"director":"Director: Stamatis Tsarouchas","genre":"Comedy","rating":5.9,"title":"Oi gennaioi tis Samothrakis"}