{"summary":"London, 1944: SOE's section for French ops parachute 4 women into France, plus a woman there, to free an English geologist and kill SS colonel Heindrich.","cast":"Sophie Marceau|Julie Depardieu|Marie Gillain|Déborah François|Moritz Bleibtreu|Maya Sansa|Julien Boisselier|Vincent Rottiers|Volker Bruch|Robin Renucci|Xavier Beauvois|Colin David Reese|Jurgen Mash|Conrad Cecil|Alexandre Jazede|David Capelle|Wolfgang Pissors|Chantal Garrigues|James Gerard|Edward Hamilton-Clark|Marc Bertolini|Rainer Sievert|Ashley Wanninger|Natasha Cashman|Stanislas Kemper|Simon Boyle|Olivier De Wispelaere|Johannes Oliver Hamm|David Van Severen|Sarah Tullamore|Philippe Soutan|Yves Heck|Stéphane Foenkinos|Christophe Grofer|Stefan Kollmuss|Fabian Arning|Olivier Beraud-Bedouin|Alex Lutz|Jan Oliver Schroeder|Serge Onteniente|Antoine Salomé|Andrew W. Wilson|Ida Techer|Frédéric Deltour|Romain Francisco|Benjamin Garnier","keywords":"year 1945|year 1944|1940s|woman wears a gas mask|murderess","year":2008,"director":"Director: Jean-Paul Salomé","genre":"Drama|War","rating":6.8,"title":"Espías en la sombra"}