{"summary":"Three young women vacationing in Paris find themselves whisked away to Monte Carlo after one of the girls is mistaken for a British heiress.","cast":"Selena Gomez|Katie Cassidy|Leighton Meester|Cory Monteith|Andie MacDowell|Brett Cullen|Amanda Fairbank-Hynes|Joe Camp III|Luke Bracey|Valérie Lemercier|Franck de la Personne|Máté Haumann|István Göz|Attila C. Arpa|Joël Lefrançois|Virág Bárány|Shay Cunliffe|Barna Illyés|Dániel Mogács|Gábor Nagypál|Matt Devere|Mark C. Phelan|Pierre Boulanger|Christophe Malavoy|Catherine Tate|Giulio Berruti|Bruno Abraham-Kremer|Romain Cottard|Arnaud Aldigé|Antal Leisen|Richard Rifkin|Sophie Thompson|George Mendel|Séverine Vasselin|Vilma Szécsi|Ben O'Brien|Bernadett Kis|Éva Magyar|Wayne Brett|Kamel Laadaili|Colomba Marchetti","keywords":"tied feet|high school graduate|22 year old|21 year old|18 year old","year":2011,"director":"Director: Thomas Bezucha","genre":"Adventure|Comedy|Family|Romance","rating":5.8,"title":"Monte Carlo"}