{"summary":"When Bella Swan moves to a small town in the Pacific Northwest, she falls in love with Edward Cullen, a mysterious classmate who reveals himself to be a 108-year-old vampire.","cast":"Kristen Stewart|Sarah Clarke|Matt Bushell|Billy Burke|Gil Birmingham|Taylor Lautner|Gregory Tyree Boyce|Justin Chon|Michael Welch|Anna Kendrick|Christian Serratos|Nikki Reed|Kellan Lutz|Ashley Greene|Jackson Rathbone|Robert Pattinson|José Zúñiga|Trish Egan|Ayanna Berkshire|Ned Bellamy|Bryce Flint-Sommerville|Peter Facinelli|Solomon Trimble|Rachelle Lefevre|Cam Gigandet|Edi Gathegi|Alexander Mendeluk|Hunter Jackson|Gavin Bristol|Sean McGrath|Katie Powers|Elizabeth Reaser|Catherine Grimme|Humberto Amor|Aaron Atkins|William Joseph Elk III|Victoria Geil|Kristopher Hyatt|Stephenie Meyer|Rick Mora|Rana Morrison|Sherry Nelson|Tyler Nordby|Trip Ross|Jimmy Star|Edward Stiner|Josh Turner|Maggie-Jo Turner|Robert Zorn","keywords":"vampire|phoenix arizona|love|school|high school","year":2008,"director":"Director: Catherine Hardwicke","genre":"Drama|Fantasy|Romance","rating":5.2,"title":"Crepúsculo"}