{"summary":"Though it's been about twenty years since they have spoken with one another, two estranged soul-singing legends agree to participate in a reunion performance at the Apollo Theater to honor their recently deceased band leader.","cast":"Samuel L. Jackson|Bernie Mac|Sharon Leal|Adam Herschman|Sean Hayes|Affion Crockett|Terrell J. Ramsey|Jackie Long|Mike Epps|John Legend|Isaac Hayes|Vanessa del Rio|P.J. Byrne|Ken Davitian|Jennifer Coolidge|Sara Erikson|Soledad O'Brien|Randy Jackson|Jackie Johnson|Shane Sampson|Dylan Sampson|Bart Hansard|Michael Brouillet|Sean Goulding|Ritchie Montgomery|Clay Yocum|Juan Gabriel Pareja|Lara Grice|Paul T. Taylor|Monyetta Shaw|Jody Thompson|Maurice DuBois|Miko DeFoor|Michael Showers|Millie Jackson|Willie Hall|Ben Cauley|Charles 'Skip' Pitts|Scott Bomar|Archie 'Hubie' Turner|Art Edmaiston|Marc Franklin|Robyn l Charles|Ketrick Robinson|J.R. Taylor|Nathan Adams|Michael Franklin|Michael C. 'Mike' Allen|LaVita Brooks|NyaSimone Caldwell|Keenan R. Carter|M Charlotte Cheatham|Gary D. Earl|Ron Fagan|Ted Ferguson|Jamie Jones|Cindy McBride|Lee Ann McDade|Donald Meyers|Saffton Reed Neuman|James Paul|Joey Robinson|Franklin Ojeda Smith|Marchello Stewart|Calvin Sykes|Alicia Tennant|Kenon Walker|Thomas Wallace|Steven Whitemon","keywords":"woman on top|viagra|oral sex|topless female nudity|african american","year":2008,"director":"Director: Malcolm D. Lee","genre":"Comedy|Drama|Music","rating":6.4,"title":"Soul Men"}