{"summary":"Calm and quiet Daniel starts on Wall Street. His womanizing colleague, Tommy, encourages him to meet women. He unknowingly meets Tommy's girlfriend, Beth, and ends up in her 5 women book club. Will he find the woman?","cast":"Alexis Bledel|Scott Porter|Bryan Greenberg|Colin Egglesfield|Aaron Yoo|Andrew Stewart-Jones|Eric Thal|Andrew McCarthy|Sarah Glendening|Ursula Abbott|Kathy Searle|Anna Chlumsky|Jessalyn Wanlim|Ed Wheeler|Michael Simeoni|Trini Alvarado|Darrin Baker|Robert T. Bogue|Raymond Seiden|Megan Bones|Rana Davis|Adrian Martinez|Steve Antonucci|Monika Baskiewicz|James Thomas Bligh|Woody Boley|Luca Calvani|Clem Cheung|Christine Evangelista|Jeane Fournier|Ted Koch|Adam LeFevre|Frances Mignano|Kate Nauta|Al Roffe|Michael Sirow|Monica Steuer|Jackie Stewart|Denise Vasi|David Villalobos|Dono Cunningham|Garett Ross|Mark Schmidt","keywords":"william shakespeare character|new york city|manhattan new york city|cheating boyfriend|book club","year":2009,"director":"Director: Julio DePietro","genre":"Comedy|Romance","rating":5.8,"title":"The Good Guy"}