{"summary":"Biography of Ben Carson who grew up to be Dr. Ben Carson, a world famous neurosurgeon at Johns Hopkins.","cast":"Cuba Gooding Jr.|Kimberly Elise|Aunjanue Ellis|Harron Atkins|Ele Bardha|Loren Bass|Geoffrey Beauchamp|Tajh Bellow|Lesley Bevan|Jesse Christian|Ron Coden|Wayne David Parker|Angela Dawe|Gregory Dockery|Zac Douglass|Ithamar Enriquez|Jaishon Fisher|Michael Fitch|Erin Renee Frankfort|Danny Goldring|Alecia Hamilton|Maestro Harrell|John Hickman|Gus Hoffman|John Hoogenakker|Duncan Hursley|Sam Logan Khaleghi|Ellington King|Alondra Lozano|Mary Mac|Adam McNinch|Erick Michael|Gordon Michaels|Dennis North|Yasen Peyankov|Cheyenne Pinson|Jacqueline Pruder|Asanté Ramone|Jimmy Rhoades|Ashley L. Richardson|Jackie Ritz|Scott Stangland|Alan Stefan|Emily Sutton-Smith|Danielle Teasley-Bailey|Casey Tutton|Rick Uecker|Aileen Uytuico|Guy Van Swearingen|Matthew Elijah Webb|Reuben Yabuku|Courtney Benjamin|Zachary Borromeo|Shawntay Dalon|Ryan Falcheck|William C. Fox|Lisa Gaulzetti|Penny Gibbs|David Gibson|Dave Kilgore|Doug Kolbicz|Candace M. Laferle|Diane M. Leach|Lawrence W. Leach|Runako Marshall|Alisa Martin|McKenna Martin|Michael Marx|Curtis Matzke|Kathi J. Moore|Mark Nunez|Steven Proehl|Ray Daniel Rogers|Grace Anne Rowan|Joe Sacksteder|Tom Stewart|Morris Lee Sullivan|Steve Swanson|Sarana VerLin|Joseph Victor|Alan Wilder|Armon York Williams|Matthew Winne","keywords":"six word title|boy wears eyeglasses|eyeglasses|neurosurgeon|stethoscope","year":2009,"director":"Director: Thomas Carter","genre":"Biography|Drama","rating":7.7,"title":"El mundo en sus manos"}