{"summary":"In México City, a Cuban dancer from \"Cabaret Changó\" rescues a baby from a garbage can and decides to raise him, but her pachuco pimp gets in her way.","cast":"Ninón Sevilla|Tito Junco|Rodolfo Acosta|Rita Montaner|Ismael Pérez|Margarita Ceballos|Arturo Soto Rangel|Francisco Reiguera|Lupe Carriles|Jorge Treviño|Pedro Vargas|Luis Aceves Castañeda|Gregorio Acosta|Ricardo Adalid|Enrique Carrillo|Aurora Cortés|Lupe del Castillo|Enedina Díaz de León|Magdalena Estrada|Agustín Fernández|Rogelio Fernández|Salvador Godínez|Leonor Gómez|Carlos León|Margarito Luna|Elena Luquín|Estela Matute|Álvaro Matute|Gloria Mestre|Chimi Monterrey|Inés Murillo|Yolanda Ortiz|Ignacio Peón|Dámaso Pérez Prado|Enriqueta Reza|Carlos Riquelme|Ángela Rodríguez|Aurora Ruiz|Hernán Vera|Hilda Vera|Acela Vidaurri","keywords":"zoot suit|hep cat|swing dance|spanish noir|pimp","year":1951,"director":"Director: Emilio Fernández","genre":"Crime|Drama|Musical|Thriller","rating":7.5,"title":"Víctimas del pecado"}