{"summary":"A woman from the lower class desperately tries to get her daughter into the movies.","cast":"Anna Magnani|Walter Chiari|Tina Apicella|Gastone Renzelli|Tecla Scarano|Lola Braccini|Arturo Bragaglia|Nora Ricci|Vittorina Benvenuti|Linda Sini|Teresa Battaggi|Gisella Monaldi|Amalia Pellegrini|Luciana Ricci|Giuseppina Arena|Liliana Mancini|Alessandro Blasetti|Vittorio Musy Glori|Mario Chiari|Luigi Filippo D'Amico|George Tapparelli|Scuola di Ballo del Teatro dell'Opera|Orchestra Sinfonica Nazionale della Rai|Coro della Radiotelevisione Italiana|Luciano Caruso|Michele Di Giulio|Mario Donatone|Franco Ferrara|Pietro Fumelli|Corrado Mantoni|Lilly Marchi|Sonia Marinelli|Guido Martufi|Anna Nighel|Lina Rossoni","keywords":"screen test|motion picture industry|mother daughter relationship|humiliation|audition","year":1951,"director":"Director: Luchino Visconti","genre":"Comedy|Drama","rating":7.8,"title":"Bellísima"}