{"summary":"A group of friends band together to hide the truth about a mutual friend's tragic death. They soon discover that an evil entity is in pursuit of them.","cast":"Jewel Staite|Connor Fox|Susie Abromeit|Michael Aills|Matty Ferraro|Jerry Leggio|T.W. Leshner|Jess Sylvia|Budd Bird|Douglas M. Griffin|Ryan H. Jackson|Kennon Kepper|Shadoe Knight|Sam Medina|Wallace Merck|Lawrence Turner|Monica Acosta|Joshua Aucoin|Thomas C. Daniel|Alex Hardee|Kelly Migdon|Melody Noel|Bill Rainey|Arvilla Riddick|Christine Standfill|Emily Ziegler","keywords":"insect in title|animal in title|one word title|monster","year":2010,"director":"Director: Sheldon Wilson","genre":"Horror","rating":3.4,"title":"Mothman"}