{"summary":"Herman Melville's classic novel Moby Dick, is recreated in a world where Captain Ahab and his crew search for a Great White Dragon.","cast":"Danny Glover|Vinnie Jones|Corey Sevier|Sofia Pernas|Larry Bagby|Kepa Kruse|David Morgan|Raphael Cruz|Yanique Bland|Wayne Brennan|McKay Daines|John Lyde|Scott Chun|Amy Micalizio|Brianne Aglaure|Savannah Ostler|Brandon Anderson|Christian Purser|Ryan Don Devey|Valeria Madsen|Preston Gibbs|Mark Oliphant|Gloria Hansen|Thomas J. Post|Ross Howard|David Turley|Chris Larsen|Nathan Harward|Erik Madsen|Erich Cannon|Clinton Purser|Taylor Bateman","keywords":"downward spiral|dragon|revenge|harpooner|sword and sorcery","year":2011,"director":"Director: Ryan Little","genre":"Action|Adventure|Fantasy","rating":3.4,"title":"En tiempo de dragones"}