{"summary":"During a day in their honeymoon, a couple is separated by the city's lust and the desires it produces.","cast":"Alberto Sordi|Brunella Bovo|Leopoldo Trieste|Giulietta Masina|Ernesto Almirante|Lilia Landi|Fanny Marchiò|Gina Mascetti|Jole Silvani|Enzo Maggio|Anna Primula|Mimo Billi|Armando Libianchi|Ugo Attanasio|Giulio Moreschi|Elettra Zago|Piero Antonucci|Aroldino the Comedian|Antonio Acqua|Lalla Ambraziejus|Silvia De Vietri|Rino Leandri|Guglielmo Leoncini|Ettore Maria Margadonna|Carlo Mazzoni|Giorgio Salvioni","keywords":"italy|newlywed|honeymoon|boat|sword","year":1952,"director":"Director: Federico Fellini","genre":"Comedy|Drama","rating":7.2,"title":"El jeque blanco"}