{"summary":"Man investigates the disappearance of two of his friends who were the guests of a sinister Austrian count.","cast":"Richard Greene|Boris Karloff|Stephen McNally|Rita Corday|Lon Chaney Jr.|John Hoyt|Michael Pate|Nancy Valentine|Tudor Owen|Henry Corden|Otto Waldis|Chet Brandenburg|Ralph Brooks|Forest Burns|Wheaton Chambers|Leslie Denison|Jimmy Dime|Roy Engel|Joe Gilbert|James Gonzalez|Chuck Hamilton|Paul Kruger|Richard LaMarr|Paul Maxey|Frank Mills|William H. O'Brien|Jack Perrin|Jack Perry|Bruce Riley|Victor Romito|John Roy|Bert Stevens|Bernard Szold","keywords":"woman in jeopardy|murder|psychotronic film|human animal fight|brutality","year":1952,"director":"Director: Nathan Juran","genre":"Horror|Mystery|Thriller","rating":6.4,"title":"El castillo del ogro"}