{"summary":"The poignant yet humor filled story about a single mother of a teenager severely impacted by autism, forced to reckon with her daughter's future. As her child becomes an adult, what used to... See full summary »","cast":"Beth Broderick|Ashley Rickards|Aramazd Stepanian|Promotion|Peter Binswanger|Greg Germann|Maui|Denise Dowse|Jon Shestack|Reno|Jay Sincere|Matthew Antonio Grillo Russell|Angela Grillo|Sheridan Cole|Marisa Laurance|Ming Cho|JR Bourne|Tamaira Danyluk|Fonda Jefferson|Maynor Lopez|Oscar Ornela Jr.|Brooke Star|Michael E. Wise|Judy Mora|Scarlett Walker|Tomica Baquet|Kristina Hornbek|Tommy Martin|Paul B. Price|Elaine Hall|Matthew Derba|Shannon Latimer|Beny C. Valde|Virginia B. Valde|John Yonover|Matthew Yonover|Cannelle Causse|Casey Martin|Jordan Roberts|Ashley Renee Saunders|Ruben Gonzalez|J.B. Popplewell|Peter Blanchett|Lauryn King|Enrique Zaldua|Charles Larson|Salvatore Camarillo|Luke Rothschild|Zach Palmer","keywords":"love|single mother|autism|f rated|female protagonist","year":2011,"director":"Director: Janet Grillo","genre":"Drama","rating":6.2,"title":"Fly Away"}