{"summary":"Janne, a 60 year old party promoter is arranging a nightclub at the annual tennis week in the small coastal town of Båstad, where he also teams up with his older sister Jackie. But an ... See full summary »","cast":"Johannes Brost|Peter Carlberg|Léonore Ekstrand|Charlotte Wandt|August Wittgenstein|Stefan Huynh|Simas Lindesis|Peter Lorentzon|Henrik Lilliér|Migle Polikeviciute|Rikard Johansson|Jennifer Lila|Etienne Petersén|Malou Stiller|Michael Preber|Carl Johan De Geer|Marianne Hallberg|Rainer Gerdes|Ludvig Nilson|Viveka Thalin|Parisa Rezai Lindorm|Carl Kumlin|A.J. Trenear|Ilja Karilampi|Christian Carloni|Karin Hallén|Kelly Marlow","keywords":"eastern europe","year":2011,"director":"Director: Axel Petersén","genre":"Drama|Thriller","rating":5.4,"title":"Avalon"}