{"summary":"A young playboy who learns he has one month until he becomes infertile sets out to procreate as much as possible.","cast":"Ryan Kwanten|Sarah Snook|Ryan Corr|Bojana Novakovic|Susan Prior|Lewis Fitz-Gerald|Kathryn Beck|Belinda Bromilow|Zoe Carides|Alice Parkinson|Lulu McClatchy|Daniel Henshall|Andrew Ryan|Sam North|Apollo Kanakis|Tasneem Roc|Katie Wall|Laura Brent|Lucy Coleman|Adele Vuko|Annalouise Paul|Clare Bowen|Brianna Sinclair|Charlie Clancey-Agius|Billy Beetson|Dana Bettine|Loughlin Reynolds|Amanda Sallybanks|Beau Lester|Troy Henman|Taryn Brine|Marlon Dance-Hooi|Zac Deane|Yolandi Franken|Chantelle Jamieson|Andrew Johnston|Alice Lanesbury|Gemma Laurelle|Tracey Lee Maxwell|Stephanie May|Margareta Moir|David Molloy|Nicole Pastor|Dilshan Rain|Cristina Ventresca|Dave White|Adnan Zey","keywords":"testicular cancer|sperm bank|parenthood|male nudity|male in shower","year":2012,"director":"Director: Peter Templeman","genre":"Comedy|Romance","rating":5.8,"title":"Not Suitable for Children"}