{"summary":"Two brothers team up to battle a creature under the bed, in what is being described as a \"suburban nightmare\" tale.","cast":"Jonny Weston|Gattlin Griffith|Peter Holden|Musetta Vander|Kelcie Stranahan|Bryan Rasmussen|Nikki Griffin|Tyler Steelman|Sam Kindseth|Ivan Djurovic|Ron Roggé|Garrett Jones|Walter Miranda|Griff Kohout|Kris Holmes|Stephanie Hernandez|Travis Berens|Mario E. Garcia|Sarmarie Klein|Alyssa Elle Steinacker","keywords":"stepmother|father son relationship|trauma|monster|teenage boy","year":2012,"director":"Director: Steven C. Miller","genre":"Drama|Horror","rating":4.6,"title":"Under the Bed"}