{"summary":"The members of a dysfunctional family begin to reinvent themselves thanks to the exchange student who moves in with them.","cast":"Vivian Dierickx|Jacqueline Blom|Ton Kas|Tomer Pawlicki|Abe Dijkman|Rafael Gareisen|Anandi Gall|Freerk Bos|Flip Filz|Giam Kwee|Frans de Wit|Nicanor Zinga|Patricio Wiedermann|Stefan de Walle|Freddie Tratlehner|Loes Kok|David Markx|Stella Mever|Nina Tesselaar|Minou van den Berg|Lotte van der Hoek|Kelly van der Waals|Giam Kwee","keywords":"teenage girl|loss of virginity|girl|coming of age|school","year":2012,"director":"Director: Michiel ten Horn","genre":"Drama","rating":6.5,"title":"Eva van End"}