{"summary":"The team of people who saved Winter's life reassemble in the wake of her surrogate mother's passing in order to find her a companion so she can remain at the Clearwater Marine Hospital.","cast":"Harry Connick Jr.|Ashley Judd|Nathan Gamble|Kris Kristofferson|Cozi Zuehlsdorff|Morgan Freeman|Austin Stowell|Betsy Landin|Juliana Harkavy|Austin Highsmith|Tom Nowicki|Charles Martin Smith|Denis Arndt|Carlos Gómez|Bethany Hamilton|Julia Jordan|Lee Karlinsky|Kim Ostrenko|Tom Hillmann|Amanda Powell|Taylor Blackwell|Denisea Wilson|Lauren O'Quinn|Alana Cavanaugh|Madison Absher|Cassie Livingston|Tamara Austin|Jessica Fernandez|Amy Jordan|Damon Sementilli|Jennifer De Castroverde|Jim R. Coleman|Raheem Babalola|David Yates|Abby Stone|Camelle Zodrow|Hope Hanafin|Howard Berger|Alex Diaz|Jeff Edwards|David Grasso|Carey Jones|David Wogh|Brian Leone|Mina Nicole Alexis|Misty Autery|Venessa Baez|Marmaduke Bin Laden|Bradley Bowen|Cayla Brady|Jessica Braswell|Parker Brenneman|Ashley Brown|Tanichee Cain|Alex Cauler|Nick Cauler|Kellyann Cernese|Carlyn Cosby-Phillips|John E. Crowther|Ellen Marguerite Cullivan|Wendy Jo Davis|Gloria de Luna|Christopher De Stefano|Jon DeLuzio|Audrey Dempster|Cherie Dempster|Emma Dempster|Scott Dumas|Andrew Durliat|Omar Elkalyoubie|Darin Ferraro|Frenchi Firecracker|Jeremy Fore|Amy Fox|Rosetta Gadson|Juli Goldstein|Johanna R. Griesé|Edward Hanlon|Winston Haynes|Melissa Heaton|Steve Heinz|Randy Herman|Nicholas Ryan Hernandez|Clay Higgins|Veronica Hilburn|Jacob Hoy|Evan Huit|Nicolette Huit|Ashley Nicole Hutto|Annie Jamison|Rich Keen|Mark Kelliher|Autumn Klein|Sierra Klein|Megan Kneiblher|Kasity Koehn|Amanda Lade|Joshua Lagos|Alivia Latimer|Christopher Lavigne|Tommy Lentsch|Mary Leonard|Brittany Linden|Douglas Lopez|Aaron Maltzman|Bella Maltzman|Ethan Maltzman|Jared Maltzman|Lucas Martin|Madison Maxwell|Andrew McKeough|Malcolm Modele|Kevin Moody|Jayce Mroz|Matthew Nardozzi|Dena Neal|Aaron Quick Nelson|Michael Newman|Ashley Nicole|Tom Ohmer|Garrett Palmer|Kamryn Palmer|Noah Perabo|Gustavo Perez|Sherri Piper|Kayda Rae|Dylan Ramus-Wright|Kelly Riese|Thia Marie Sandefur|Jon Schueler|Erich Schuett|Jen Sharlow|John L. Smith Jr.|Rory Smith|Gail Soltys|Christopher Sommerhalter|Ashley Sperrazza|Chad Stevens|Kira Taylor|Catherine Thornton|Zachary Vazquez|Adrianne Walsh|Benjamin Weaver|Trevor Wesley|Caleb Wild|Winter|Ilia Wolfe|Thaddeus Ygnacio|Nate Zahrt","keywords":"no opening credits|pelican|dolphin|purple gloves|latex gloves","year":2014,"director":"Director: Charles Martin Smith","genre":"Drama|Family","rating":6.4,"title":"La gran aventura de Winter el delfín 2"}