{"summary":"Some of the chapters from Arabian Nights are adapted to a modern Portugal in this epic.","cast":"Crista Alfaiate|Miguel Gomes|Maria Rueff|Bruno Bravo|Rogério Samora|Dinarte Branco|Américo Silva|Carloto Cotta|Diogo Dória|Adriano Luz|Basirou Diallo|Luísa Cruz|Cristina Carvalhal|Chico Chapas|Susana Afonso Lopes|Tiago Fagulha|Sabrina Lopes|Carlos Loureiro|Fernanda Loureiro|Louison Tresallet","keywords":"unemployment|economic crisis|reference to the arabian nights|1001 nights|scheherazade character","year":2015,"director":"Director: Miguel Gomes","genre":"Drama","rating":7.0,"title":"Las mil y una noches: volumen 1. El inquieto"}