{"summary":"A rogue assassin is taking out military leaders, and Brandon gets word that his father is one. He tries to track down the killer, finds out that his father isn't dead and realizes that his superior officers are using him as bait to track the killer.","cast":"Tom Berenger|Chad Michael Collins|Doug Allen|Dominic Mafham|Mercedes Mason|Mark Lewis Jones|Nestor Serrano|Dennis Haysbert|Alex Roe|Yana Marinova|George Zlatarev|Woon Young Park|Patrick Garrity|Nikolay Chilov|Danko Jordanov|Asen Asenov|Dimiter Doichinov|Vasil Enev|Raicho Vasilev","keywords":"east berlin germany|view through rifle scope|assassin|military|arm sling","year":2014,"director":"Director: Don Michael Paul","genre":"Action|Thriller|War","rating":5.4,"title":"Sniper: El legado"}