{"summary":"Meera, a beautiful Australian woman of Indian origin, living in Sydney as a single mother, she follows her dreams, instead of that of her parents'. She falls in love with a man named Will, ... See full summary »","cast":"Brett Lee|Tannishtha Chatterjee|Supriya Pathak|Akash Khurana|Maya Sathi|John Howard|Arka Das|Sarah Roberts|Nicholas Brown|Adam Dunn|Kumud Merani|Gulshan Grover|Kashif Amjad|Anupam Sharma|Pallavi Sharda|Deji Adiatu|Abhinav Bali|Laura Bunting|Zoe Cahill|Warren Ekermans|Rob Flanagan|Evan Gong|Stephen Hunter|Vikrant Kishore|Heather Maltman|Michele-Antonio Mattiuzzi|Bali Padda|Sakshi Prasad|Mark Sheridan|Dia Soni|Andy Trieu|Maha Wilson|David E. Woodley|Susan Ling Young","keywords":"indian|australia","year":2015,"director":"Director: Anupam Sharma","genre":"Comedy|Drama|Romance","rating":5.6,"title":"UNindian"}