{"summary":"Bill Williamson returns to bring down the president of the United States and his Secret Service detail.","cast":"Brendan Fletcher|Bruce Blain|Loretta Walsh|Zain Meghji|Steve Baran|Ryan McDonell|Scott Patey|Yan-Kay Crystal Lowe|Anthony Rogers|Dan Shea|Brian Brisco|Matthew Sulzle|Brennan Walstrom|Tyson Arner|Shawn Stewart|Colby Chartrand|Raymond Sammel|John Sampson|Kye Walstrom|John Ulmer|Jovan Nenadic|Owen Walstrom|Adrian Persad|Trevor Jones|Deb Mac|Rick Pearce|Janina Dall|Mike Carpenter|Uwe Boll|Victor Formosa|Ralph Steiger","keywords":"third part|blood splatter|fbi agent|shoot out|police","year":2016,"director":"Director: Uwe Boll","genre":"Action|Crime|Thriller","rating":4.8,"title":"Rampage: President Down"}