{"summary":"A musical set mainly in a corporate high-rise. Two assistants, Lee Xiang and Kat, start new jobs at the financial firm Jones & Sunn. Lee Xiang is an earnest young man who naively enters the... See full summary »","cast":"Sylvia Chang|Yun-Fat Chow|Eason Chan|Tang Wei|Ziyi Wang|Yueting Lang|Eddie Cheung|Tien-Hsin|Stephanie Che|Timmy Hung|Kin-Kwan Chu|Adrian Wong|Catherine Chau|Mimi Chi Yan Kung|Hoi-Pang Lo|Philip Keung|Amy Fan|Vincent Sze|Ling-To Yuen|Wah-Shan Ng|Owen Ng|Sam Yu-Sum Chan|Ronald Yan|Wah-Ho Wong|Sze Yan Wong|Luvin Ching-Wai Ho|Iva Law|Kin-Man Ho|Margiela Kwok|Ka Ying Cheung|David Mersault|Benjamin Yeung|Ka-Ho Yeung|James Kazama|Pak-Yin Fung|Monica Man-Ying Hong|Kathy Wu","keywords":"man slaps a woman|woman slaps a man|finance|face slap|ceo","year":2015,"director":"Director: Johnnie To","genre":"Comedy|Musical|Romance","rating":6.1,"title":"Hua li shang ban zu"}