{"summary":"World War I ace Dick Courtney derides the leadership of his superior officer, but Courtney is soon promoted to squadron commander and learns harsh lessons about sending subordinates to their deaths.","cast":"Richard Barthelmess|Douglas Fairbanks Jr.|Neil Hamilton|Frank McHugh|Clyde Cook|James Finlayson|Gardner James|William Janney|Edmund Breon|Jack Ackroyd|Harry Allen|Morey Eastman|Howard Hawks|Jack Jordan|Dave O'Brien","keywords":"trench warfare|suicide mission|strafing|self sacrifice|royal flying corps","year":1930,"director":"Director: Howard Hawks","genre":"Action|Drama|War","rating":7.2,"title":"La escuadrilla del amanecer"}