{"summary":"A priest in a poor community lives a charitable life in accordance with his religious principles, but many others do not return the favor.","cast":"Marga López|Francisco Rabal|Rita Macedo|Ignacio López Tarso|Ofelia Guilmáin|Luis Aceves Castañeda|Noé Murayama|Rosenda Monteros|Jesús Fernández|Ada Carrasco|Antonio Bravo|Aurora Molina|David Reynoso|Efraín Arauz|Manuel Arvide|Socorro Avelar|Edmundo Barbero|Victorio Blanco|Lupe Carriles|Arturo Castro 'Bigotón'|José Chávez|Raúl Dantés|Felipe de Flores|Enedina Díaz de León|José Luis Fernández|Lidia Franco|Salvador Godínez|Leonor Gómez|Cecilia Leger|Blanca Marroquín|Roberto Meyer|Inés Murillo|Diana Ochoa|Pilar Pellicer|José Peña|Ignacio Peón|Ramón Sánchez|Salvador Terroba|Paz Villegas|Isabel Vázquez 'La Chichimeca'|Amado Zumaya","keywords":"dwarf|1950s|belonging|mexican|salvation","year":1959,"director":"Director: Luis Buñuel","genre":"Drama","rating":7.9,"title":"Nazarín"}