{"summary":"His ideals challenged by life as a conscript in war-time Japan's military, a pacifist faces ever greater tests in his fight for survival.","cast":"Tatsuya Nakadai|Michiyo Aratama|Tamao Nakamura|Yûsuke Kawazu|Chishû Ryû|Taketoshi Naitô|Kyôko Kishida|Reiko Hitomi|Keijirô Morozumi|Kôji Kiyomura|Nobuo Kaneko|Fujio Suga|Tatsuya Ishiguro|Kazuo Kitamura|Toshio Takahara|Akira Yamanouchi|Hiroshi Nihon'yanagi|Kôichi Hayashi|Kô Mihashi|Kichijirô Ueda|Saburô Bôya|Masahiko Naruse|Takashi Sue|Kin Sugai|Miyoko Nakamura|Yoshie Minami|Noriko Ishimoto|Takayuki Shindô|Fumie Kitahara|Gen'ya Nagai|Hideo Fukuhara|Tadayoshi Hirosawa|Tetsuo Mizoi|Daijirô Minami|Kanji Ôsugi|Mamoru Hirata|Hideo Hirosawa|Takao Tsuge|Kôtarô Hirasawa|Masatoshi Kanematsu|Yuichi Kikuchi|Hachirô Maruyama|Akira Kimura|Yasuo Minami|Hideko Aki|Mikiko Suzuki|Yumiko Oguri|Kazuko Hirano|Yoshiko Watanabe|Yôko Hayashi|Fumiko Kondô|Edo Kîn|Ronarudo Serufu|Pôru Rafaero|Wiriamu Bassun|Henrî Ban|Hideko Takamine","keywords":"japanese|soviet|russian|prisoner of war|defeat","year":1961,"director":"Director: Masaki Kobayashi","genre":"Drama|History|War","rating":8.8,"title":"La condición humana III: La plegaria del soldado"}