{"summary":"Junie Moon's face has been disfigured by ill-gotten burns, and she depends on her wit and her friends, Warren and Arthur, to cope. Yearning for independence, the three leave the hospital ... See full summary »","cast":"Wayne Tippit|Guy Sorel|Clarice Taylor|Liza Minnelli|Barbara Logan|Ben Piazza|Robert Moore|Ken Howard|Anne Revere|James Coco|James Beard|Elaine Shore|Leonard Frey|Angelique Pettyjohn|Kay Thompson|Fred Williamson|Richard O'Barry|Gina Collens|Emily Yancy|Paul Barstow|Ulla Bomser|Julie Bovasso|Cynthia Korman|Anne Larson|Nancy Marchand|Lynn Milgrim|Pacific Gas & Electric|James David Pasternak|Pete Seeger|Donald Warnock|Jim Begg|Donald Clement|Mauraine Lorimer|Connie Mason|Madge West","keywords":"champagne|cognac|gin|beer|grand marnier","year":1970,"director":"Director: Otto Preminger","genre":"Comedy|Drama|Romance","rating":6.2,"title":"Dime que me amas, Junie Moon"}