{"summary":"A sex-crimes specialist from New York travels to the Philippines to help his friend, a Manila homicide detective, solve a series of murders.","cast":"Robert Winston|Katherine Henryk|Yvonne Nielson|Vic Diaz|Vic Silayan|Eddie Infante|Bruno Punzalan|Judy Dennis|Max Roio|Ching Tello|Minda Morena|Isidro Francisco|Felix Marfil","keywords":"rapid aging|sex crime|murder|murder investigation|death","year":1971,"director":"Director: Newt Arnold","genre":"Horror","rating":4.5,"title":"Blood Thirst"}