{"summary":"Two Geisha with a connection to a young man deal with life's hardships.","cast":"Mitsuko Yoshikawa|Akio Isono|Sumiko Mizukubo|Reikichi Kawamura|Ryuko Fuji|Yôko Fujita|Tomio Aoki|Chôko Iida|Kinuko Wakamizu|Ryôichi Takeuchi|Tokuji Kobayashi|Arai Atsushi|Ureo Egawa|Fusako Fujita|Shin'ichi Himori|Shôichi Kofujita|Kyôko Mitsukawa|Kotarô Sekiguchi|Mitsuru Wakamiya|Teruko Wakamizu","keywords":"","year":1933,"director":"Director: Mikio Naruse","genre":"Drama","rating":7.1,"title":"Kimi to wakarete"}