{"summary":"After a six year journey, the Spaceship Cyrno lands on the planet TEM 4 from where they had received a call for help. Strangely enough, the Temers deny having sent this message. As ... See full summary »","cast":"Jana Brejchová|Alfred Struwe|Ekkehard Schall|Milan Beli|Silvia Popovici|Violeta Andrei|Leon Niemczyk|Regine Heintze|Mihai Mereuta|Stefan Mihailescu-Braila|Aurelia Dumitrescu|Zephi Alsec","keywords":"low budget sci fi movie|spaceship|outer space","year":1976,"director":"Director: Gottfried Kolditz","genre":"Sci-Fi","rating":5.4,"title":"Im Staub der Sterne"}