{"summary":"A sheltered young high society woman joins the United States Army on a whim and finds herself in a more difficult situation than she ever expected.","cast":"Goldie Hawn|Eileen Brennan|Armand Assante|Robert Webber|Sam Wanamaker|Barbara Barrie|Mary Kay Place|Harry Dean Stanton|Albert Brooks|Alan Oppenheimer|Estelle Marlov|Everett Covin|Robert Hanley|Lee Wallace|James Dybas|Gretchen Wyler|Maxine Stuart|Lillian Adams|Sandy Weintraub|Tim Haldeman|Kopi Sotiropulos|Stu Nahan|J.P. Bumstead|Hal Williams|Toni Kalem|Damita Jo Freeman|Alston Ahern|P.J. Soles|Craig T. Nelson|James R. Barnett|Ray Oliver|Robin Hoff|Eddie Lewis|Carrol Davis Carson|Clay Wright|Danny Wells|Keone Young|George Roberts|Helen Baron|Paul Marin|Mimi Maynard|Alice Hirson|Wil Albert|Richard Herd|Sally Kirkland|Denise Halma|Lilyan Chauvin|David Olivier|Elie Liardet|Shirley Anthony|Stéphane Grappelli|Jack Griffin|Heather Haase|David LeBell|Nico Stevens","keywords":"female stockinged feet|pantyhose|camera shot of feet|suntan pantyhose|female protagonist","year":1980,"director":"Director: Howard Zieff","genre":"Comedy|War","rating":6.2,"title":"La recluta Benjamín"}