{"summary":"With the outbreak of WWII, the sudden call to arms will send the men of a family's estate to the front, leaving a curious adolescent alone with the remaining women of the house, in need of a warm embrace and, possibly, a daring kiss.","cast":"Thierry Tevini|Anja Schüte|Valérie Dumas|Évelyne Dandry|Elisa Servier|Jean-Yves Chatelais|Macha Méril|Hannes Kaetner|Silke Rein|Laure Dechasnel|Pierre Vernier|Jean Rougerie|Catherine Rouvel|Gaëlle Legrand|Anne Fontaine|Carmen Weber|Fanny Bastien|Jean-Louis Fortuit|Pierre Chantepie|Jean-Pierre Rambal","keywords":"loss of virginity|coming of age|adolescent|14 year old|love triangle","year":1980,"director":"Director: David Hamilton","genre":"Comedy|Drama|Romance","rating":5.5,"title":"Tiernas primas"}